b_cntr.sv
module b_cntr
// #(parameter N = 8)
(
    input logic clk, rst, en,
    output logic [7:0] Q
);

    logic [7:0] D;
    logic [7:0] buff;

    always_ff @(posedge clk, posedge rst)
        if (rst)
            buff <= 8'd0;
        else
            buff <= D;

    always_comb begin
        if (en)
            D = buff + 1;
        else
            D = buff; 
    end

    assign Q = buff;
    
endmodule

tb.sv
`timescale 1ms/10ns

module tb ();
	localparam T=10;
	logic clk, rst, en;
	logic [7:0] Q;

	//*********************************************************************
	// DUT instantiation
	//*********************************************************************
	b_cntr test (.clk(clk), .rst(rst), .en(en), .Q(Q));

	//*********************************************************************
	// clock
	//*********************************************************************
	always begin
		clk = 1'b1;
		#(T/2);
		clk = 1'b0;
		#(T/2);
	end

	//*********************************************************************
	// reset high for the first cycle
	//*********************************************************************
	initial begin
		rst = 1'b1;
		#T;
		rst = 1'b0;
	end

	//*********************************************************************
	// Test
	//*********************************************************************
	initial begin
		// Wait for reset to go low
		@(negedge rst);          
		$monitor("Q=%b", Q);

		//*****************************************************************
		// Enable is 1
		//*****************************************************************
		en = 1;
		// Wait for 100 negative edges of clk
		repeat (100) @(negedge clk);

		//*****************************************************************
		// Enable is 0
		//*****************************************************************
		en = 0;
		// Wait for 100 negative edges of clk
		repeat (100) @(negedge clk);
		en = 1;

		// continue till q = 255
		wait (Q == 255);

		// Finsh Simulation
        $finish();
		$display("TEST COMPLETE");
	end

	//********************************************************************
	// Dump the signals and variables
	//********************************************************************
	initial begin
        $dumpfile("dump.vcd");
        $dumpvars(0, tb); 
    end

endmodule

dump.vcd
$date
	Fri Dec 30 21:24:48 2022
$end
$version
	Icarus Verilog
$end
$timescale
	10ns
$end
$scope module tb $end
$var wire 8 ! Q [7:0] $end
$var reg 1 " clk $end
$var reg 1 # en $end
$var reg 1 $ rst $end
$scope module test $end
$var wire 8 % Q [7:0] $end
$var wire 1 " clk $end
$var wire 1 # en $end
$var wire 1 $ rst $end
$var reg 8 & D [7:0] $end
$var reg 8 ' buff [7:0] $end
$upscope $end
$upscope $end
$enddefinitions $end
#0
$dumpvars
b0 '
b0 &
b0 %
1$
x#
1"
b0 !
$end
#500000
0"
#1000000
b1 &
1#
1"
0$
#1500000
0"
#2000000
b10 &
b1 !
b1 %
b1 '
1"
#2500000
0"
#3000000
b11 &
b10 !
b10 %
b10 '
1"
#3500000
0"
#4000000
b100 &
b11 !
b11 %
b11 '
1"
#4500000
0"
#5000000
b101 &
b100 !
b100 %
b100 '
1"
#5500000
0"
#6000000
b110 &
b101 !
b101 %
b101 '
1"
#6500000
0"
#7000000
b111 &
b110 !
b110 %
b110 '
1"
#7500000
0"
#8000000
b1000 &
b111 !
b111 %
b111 '
1"
#8500000
0"
#9000000
b1001 &
b1000 !
b1000 %
b1000 '
1"
#9500000
0"
#10000000
b1010 &
b1001 !
b1001 %
b1001 '
1"
#10500000
0"
#11000000
b1011 &
b1010 !
b1010 %
b1010 '
1"
#11500000
0"
#12000000
b1100 &
b1011 !
b1011 %
b1011 '
1"
#12500000
0"
#13000000
b1101 &
b1100 !
b1100 %
b1100 '
1"
#13500000
0"
#14000000
b1110 &
b1101 !
b1101 %
b1101 '
1"
#14500000
0"
#15000000
b1111 &
b1110 !
b1110 %
b1110 '
1"
#15500000
0"
#16000000
b10000 &
b1111 !
b1111 %
b1111 '
1"
#16500000
0"
#17000000
b10001 &
b10000 !
b10000 %
b10000 '
1"
#17500000
0"
#18000000
b10010 &
b10001 !
b10001 %
b10001 '
1"
#18500000
0"
#19000000
b10011 &
b10010 !
b10010 %
b10010 '
1"
#19500000
0"
#20000000
b10100 &
b10011 !
b10011 %
b10011 '
1"
#20500000
0"
#21000000
b10101 &
b10100 !
b10100 %
b10100 '
1"
#21500000
0"
#22000000
b10110 &
b10101 !
b10101 %
b10101 '
1"
#22500000
0"
#23000000
b10111 &
b10110 !
b10110 %
b10110 '
1"
#23500000
0"
#24000000
b11000 &
b10111 !
b10111 %
b10111 '
1"
#24500000
0"
#25000000
b11001 &
b11000 !
b11000 %
b11000 '
1"
#25500000
0"
#26000000
b11010 &
b11001 !
b11001 %
b11001 '
1"
#26500000
0"
#27000000
b11011 &
b11010 !
b11010 %
b11010 '
1"
#27500000
0"
#28000000
b11100 &
b11011 !
b11011 %
b11011 '
1"
#28500000
0"
#29000000
b11101 &
b11100 !
b11100 %
b11100 '
1"
#29500000
0"
#30000000
b11110 &
b11101 !
b11101 %
b11101 '
1"
#30500000
0"
#31000000
b11111 &
b11110 !
b11110 %
b11110 '
1"
#31500000
0"
#32000000
b100000 &
b11111 !
b11111 %
b11111 '
1"
#32500000
0"
#33000000
b100001 &
b100000 !
b100000 %
b100000 '
1"
#33500000
0"
#34000000
b100010 &
b100001 !
b100001 %
b100001 '
1"
#34500000
0"
#35000000
b100011 &
b100010 !
b100010 %
b100010 '
1"
#35500000
0"
#36000000
b100100 &
b100011 !
b100011 %
b100011 '
1"
#36500000
0"
#37000000
b100101 &
b100100 !
b100100 %
b100100 '
1"
#37500000
0"
#38000000
b100110 &
b100101 !
b100101 %
b100101 '
1"
#38500000
0"
#39000000
b100111 &
b100110 !
b100110 %
b100110 '
1"
#39500000
0"
#40000000
b101000 &
b100111 !
b100111 %
b100111 '
1"
#40500000
0"
#41000000
b101001 &
b101000 !
b101000 %
b101000 '
1"
#41500000
0"
#42000000
b101010 &
b101001 !
b101001 %
b101001 '
1"
#42500000
0"
#43000000
b101011 &
b101010 !
b101010 %
b101010 '
1"
#43500000
0"
#44000000
b101100 &
b101011 !
b101011 %
b101011 '
1"
#44500000
0"
#45000000
b101101 &
b101100 !
b101100 %
b101100 '
1"
#45500000
0"
#46000000
b101110 &
b101101 !
b101101 %
b101101 '
1"
#46500000
0"
#47000000
b101111 &
b101110 !
b101110 %
b101110 '
1"
#47500000
0"
#48000000
b110000 &
b101111 !
b101111 %
b101111 '
1"
#48500000
0"
#49000000
b110001 &
b110000 !
b110000 %
b110000 '
1"
#49500000
0"
#50000000
b110010 &
b110001 !
b110001 %
b110001 '
1"
#50500000
0"
#51000000
b110011 &
b110010 !
b110010 %
b110010 '
1"
#51500000
0"
#52000000
b110100 &
b110011 !
b110011 %
b110011 '
1"
#52500000
0"
#53000000
b110101 &
b110100 !
b110100 %
b110100 '
1"
#53500000
0"
#54000000
b110110 &
b110101 !
b110101 %
b110101 '
1"
#54500000
0"
#55000000
b110111 &
b110110 !
b110110 %
b110110 '
1"
#55500000
0"
#56000000
b111000 &
b110111 !
b110111 %
b110111 '
1"
#56500000
0"
#57000000
b111001 &
b111000 !
b111000 %
b111000 '
1"
#57500000
0"
#58000000
b111010 &
b111001 !
b111001 %
b111001 '
1"
#58500000
0"
#59000000
b111011 &
b111010 !
b111010 %
b111010 '
1"
#59500000
0"
#60000000
b111100 &
b111011 !
b111011 %
b111011 '
1"
#60500000
0"
#61000000
b111101 &
b111100 !
b111100 %
b111100 '
1"
#61500000
0"
#62000000
b111110 &
b111101 !
b111101 %
b111101 '
1"
#62500000
0"
#63000000
b111111 &
b111110 !
b111110 %
b111110 '
1"
#63500000
0"
#64000000
b1000000 &
b111111 !
b111111 %
b111111 '
1"
#64500000
0"
#65000000
b1000001 &
b1000000 !
b1000000 %
b1000000 '
1"
#65500000
0"
#66000000
b1000010 &
b1000001 !
b1000001 %
b1000001 '
1"
#66500000
0"
#67000000
b1000011 &
b1000010 !
b1000010 %
b1000010 '
1"
#67500000
0"
#68000000
b1000100 &
b1000011 !
b1000011 %
b1000011 '
1"
#68500000
0"
#69000000
b1000101 &
b1000100 !
b1000100 %
b1000100 '
1"
#69500000
0"
#70000000
b1000110 &
b1000101 !
b1000101 %
b1000101 '
1"
#70500000
0"
#71000000
b1000111 &
b1000110 !
b1000110 %
b1000110 '
1"
#71500000
0"
#72000000
b1001000 &
b1000111 !
b1000111 %
b1000111 '
1"
#72500000
0"
#73000000
b1001001 &
b1001000 !
b1001000 %
b1001000 '
1"
#73500000
0"
#74000000
b1001010 &
b1001001 !
b1001001 %
b1001001 '
1"
#74500000
0"
#75000000
b1001011 &
b1001010 !
b1001010 %
b1001010 '
1"
#75500000
0"
#76000000
b1001100 &
b1001011 !
b1001011 %
b1001011 '
1"
#76500000
0"
#77000000
b1001101 &
b1001100 !
b1001100 %
b1001100 '
1"
#77500000
0"
#78000000
b1001110 &
b1001101 !
b1001101 %
b1001101 '
1"
#78500000
0"
#79000000
b1001111 &
b1001110 !
b1001110 %
b1001110 '
1"
#79500000
0"
#80000000
b1010000 &
b1001111 !
b1001111 %
b1001111 '
1"
#80500000
0"
#81000000
b1010001 &
b1010000 !
b1010000 %
b1010000 '
1"
#81500000
0"
#82000000
b1010010 &
b1010001 !
b1010001 %
b1010001 '
1"
#82500000
0"
#83000000
b1010011 &
b1010010 !
b1010010 %
b1010010 '
1"
#83500000
0"
#84000000
b1010100 &
b1010011 !
b1010011 %
b1010011 '
1"
#84500000
0"
#85000000
b1010101 &
b1010100 !
b1010100 %
b1010100 '
1"
#85500000
0"
#86000000
b1010110 &
b1010101 !
b1010101 %
b1010101 '
1"
#86500000
0"
#87000000
b1010111 &
b1010110 !
b1010110 %
b1010110 '
1"
#87500000
0"
#88000000
b1011000 &
b1010111 !
b1010111 %
b1010111 '
1"
#88500000
0"
#89000000
b1011001 &
b1011000 !
b1011000 %
b1011000 '
1"
#89500000
0"
#90000000
b1011010 &
b1011001 !
b1011001 %
b1011001 '
1"
#90500000
0"
#91000000
b1011011 &
b1011010 !
b1011010 %
b1011010 '
1"
#91500000
0"
#92000000
b1011100 &
b1011011 !
b1011011 %
b1011011 '
1"
#92500000
0"
#93000000
b1011101 &
b1011100 !
b1011100 %
b1011100 '
1"
#93500000
0"
#94000000
b1011110 &
b1011101 !
b1011101 %
b1011101 '
1"
#94500000
0"
#95000000
b1011111 &
b1011110 !
b1011110 %
b1011110 '
1"
#95500000
0"
#96000000
b1100000 &
b1011111 !
b1011111 %
b1011111 '
1"
#96500000
0"
#97000000
b1100001 &
b1100000 !
b1100000 %
b1100000 '
1"
#97500000
0"
#98000000
b1100010 &
b1100001 !
b1100001 %
b1100001 '
1"
#98500000
0"
#99000000
b1100011 &
b1100010 !
b1100010 %
b1100010 '
1"
#99500000
0"
#100000000
b1100100 &
b1100011 !
b1100011 %
b1100011 '
1"
#100500000
b1100011 &
0#
0"
